pg_airman_mcp/__init__.py
pg_airman_mcp/artifacts.py
pg_airman_mcp/server.py
pg_airman_mcp/database_health/__init__.py
pg_airman_mcp/database_health/buffer_health_calc.py
pg_airman_mcp/database_health/connection_health_calc.py
pg_airman_mcp/database_health/constraint_health_calc.py
pg_airman_mcp/database_health/database_health.py
pg_airman_mcp/database_health/index_health_calc.py
pg_airman_mcp/database_health/init.sql
pg_airman_mcp/database_health/replication_calc.py
pg_airman_mcp/database_health/sequence_health_calc.py
pg_airman_mcp/database_health/vacuum_health_calc.py
pg_airman_mcp/explain/README.md
pg_airman_mcp/explain/__init__.py
pg_airman_mcp/explain/explain_plan.py
pg_airman_mcp/index/dta_calc.py
pg_airman_mcp/index/index_opt_base.py
pg_airman_mcp/index/llm_opt.py
pg_airman_mcp/index/presentation.py
pg_airman_mcp/sql/__init__.py
pg_airman_mcp/sql/bind_params.py
pg_airman_mcp/sql/extension_utils.py
pg_airman_mcp/sql/index.py
pg_airman_mcp/sql/safe_sql.py
pg_airman_mcp/sql/sql_driver.py
pg_airman_mcp/top_queries/__init__.py
pg_airman_mcp/top_queries/top_queries_calc.py
pg_airman_mcp-0.5.0.dist-info/METADATA
pg_airman_mcp-0.5.0.dist-info/WHEEL
pg_airman_mcp-0.5.0.dist-info/entry_points.txt
pg_airman_mcp-0.5.0.dist-info/licenses/LICENSE
pg_airman_mcp-0.5.0.dist-info/RECORD
