Metadata-Version: 2.4
Name: pg-airman-mcp
Version: 0.5.0
Summary: PostgreSQL Tuning and Analysis Tool
Author-email: Johann Schleier-Smith <jssmith@crystal.cloud>, Giulio Calacoci <giulio.calacoci@enterprisedb.com>, Bilge Ince <bilge.ince@enterprisedb.com>
License-Expression: MIT
License-File: LICENSE
Requires-Python: >=3.12
Requires-Dist: attrs>=25.3.0
Requires-Dist: humanize>=4.8.0
Requires-Dist: instructor>=1.7.9
Requires-Dist: mcp>=1.9.2
Requires-Dist: pglast==7.2.0
Requires-Dist: psycopg-pool>=3.2.6
Requires-Dist: psycopg[c]>=3.2.8
Requires-Dist: pytest-cov>=7.0.0
